signDNE/__init__.py
signDNE/_signDNE_cli.py
signDNE/signDNE.py
signDNE/utils.py
signDNE/examples/example.py
signDNE/tests/test_signDNE.py
signDNE/tests/test_signDNE_cli.py
signDNE/tests/test_utils.py
signdne-0.1.4.dist-info/licenses/LICENSE
signdne-0.1.4.dist-info/METADATA
signdne-0.1.4.dist-info/WHEEL
signdne-0.1.4.dist-info/entry_points.txt
signdne-0.1.4.dist-info/top_level.txt
signdne-0.1.4.dist-info/RECORD
