Metadata-Version: 2.4
Name: signDNE
Version: 0.1.4
Summary: SignDNE is a Python package for calculating ariaDNE and its sign-oriented extension
Author-email: Felix Risbro Hjerrild <felix+signDNE@hjerrild.org>
License-Expression: GPL-3.0-or-later
Project-URL: Homepage, https://github.com/frisbro303/SignDNE
Classifier: Programming Language :: Python :: 3
Classifier: Operating System :: OS Independent
Requires-Python: >=3.8
License-File: LICENSE
Requires-Dist: scipy
Requires-Dist: trimesh
Requires-Dist: numpy
Requires-Dist: pyvista
Requires-Dist: pandas
Requires-Dist: networkx
Requires-Dist: rtree
Requires-Dist: pyglet<2
Dynamic: license-file
